bytecodemanipulation/Emulator.py
bytecodemanipulation/Mixin.py
bytecodemanipulation/MutableFunction.py
bytecodemanipulation/MutableFunctionHelpers.py
bytecodemanipulation/Optimiser.py
bytecodemanipulation/Specialization.py
bytecodemanipulation/TypeEnforcer.py
bytecodemanipulation/__init__.py
bytecodemanipulation/annotated_std.py
bytecodemanipulation/data_loader.py
bytecodemanipulation/mixin_util.py
bytecodemanipulation/optimise_self.py
bytecodemanipulation/optimiser_util.py
bytecodemanipulation/util.py
bytecodemanipulation/assembler/AbstractBase.py
bytecodemanipulation/assembler/Emitter.py
bytecodemanipulation/assembler/Lexer.py
bytecodemanipulation/assembler/Parser.py
bytecodemanipulation/assembler/__init__.py
bytecodemanipulation/assembler/hook.py
bytecodemanipulation/assembler/syntax_errors.py
bytecodemanipulation/assembler/target.py
bytecodemanipulation/assembler/util/CommonUtil.py
bytecodemanipulation/assembler/util/__init__.py
bytecodemanipulation/assembler/util/parser.py
bytecodemanipulation/assembler/util/tokenizer.py
bytecodemanipulation/data/__init__.py
bytecodemanipulation/data/shared/__init__.py
bytecodemanipulation/data/shared/builtin_spec.py
bytecodemanipulation/data/shared/expressions/AttributeAccessExpression.py
bytecodemanipulation/data/shared/expressions/CompoundExpression.py
bytecodemanipulation/data/shared/expressions/ConstantAccessExpression.py
bytecodemanipulation/data/shared/expressions/DerefAccessExpression.py
bytecodemanipulation/data/shared/expressions/DiscardValueExpression.py
bytecodemanipulation/data/shared/expressions/DynamicAccessExpression.py
bytecodemanipulation/data/shared/expressions/GlobalAccessExpression.py
bytecodemanipulation/data/shared/expressions/GlobalStaticAccessExpression.py
bytecodemanipulation/data/shared/expressions/LocalAccessExpression.py
bytecodemanipulation/data/shared/expressions/MacroAccessExpression.py
bytecodemanipulation/data/shared/expressions/MacroParameterAcessExpression.py
bytecodemanipulation-0.3.5.dist-info/LICENSE
bytecodemanipulation-0.3.5.dist-info/METADATA
bytecodemanipulation-0.3.5.dist-info/WHEEL
bytecodemanipulation-0.3.5.dist-info/top_level.txt
bytecodemanipulation-0.3.5.dist-info/RECORD
