Metadata-Version: 2.1
Name: bytecodemanipulation
Version: 0.3.5
Summary: High level python bytecode manipulation
Home-page: https://github.com/uuk0/PyBytecodeManipulator
Author: uuk
Author-email: uuk1301@gmail.com
Project-URL: Bug Tracker, https://github.com/uuk0/PyBytecodeManipulator/issues
Classifier: Programming Language :: Python :: 3.10
Classifier: Programming Language :: Python :: 3.11
Classifier: License :: OSI Approved :: MIT License
Classifier: Operating System :: OS Independent
Classifier: Development Status :: 2 - Pre-Alpha
Classifier: Programming Language :: Python :: Implementation :: CPython
Requires-Python: >=3.10
License-File: LICENSE
